{"content":[{"id":"6de80afb","settings":{"css_classes":"design-gradient","padding":{"unit":"%","top":"3","right":"0","bottom":"0","left":"0","isLinked":false},"padding_tablet":{"unit":"%","top":"","right":"","bottom":"","left":"","isLinked":true},"padding_mobile":{"unit":"%","top":"","right":"","bottom":"","left":"","isLinked":true}},"elements":[{"id":"160750f3","settings":{"_column_size":100,"_inline_size":null},"elements":[{"id":"5e6afa57","settings":{"title":"Through the Fog with Your AIR CO. blog","typography_typography":"custom","typography_font_family":"Sansita","typography_font_size":{"unit":"rem","size":4,"sizes":[]},"typography_font_weight":"400","typography_font_size_tablet":{"unit":"rem","size":3,"sizes":[]},"typography_font_size_mobile":{"unit":"rem","size":2,"sizes":[]},"typography_text_transform":"uppercase","pa_condition_repeater":[{"_id":"66dac9e"}],"_padding":{"unit":"%","top":"0","right":"0","bottom":"2","left":"0","isLinked":false},"_padding_tablet":{"unit":"%","top":"","right":"","bottom":"","left":"","isLinked":true},"_padding_mobile":{"unit":"%","top":"","right":"","bottom":"","left":"","isLinked":true}},"elements":[],"isInner":false,"widgetType":"heading","elType":"widget"},{"id":"dc58693","settings":{"classic_meta_separator":"\/\/\/","classic_read_more_text":"Read More \u00bb","cards_meta_separator":"\u2022","cards_read_more_text":"Read More \u00bb","full_content_meta_separator":"\/\/\/","pagination_page_limit":"5","pagination_prev_label":"&laquo; Previous","pagination_next_label":"Next &raquo;","text":"Load More","load_more_no_posts_custom_message":"No more posts to show","classic_columns":"2","pagination_type":"prev_next","classic_meta_data":["date"],"classic_title_typography_typography":"custom","classic_title_typography_font_family":"Sansita","classic_title_typography_font_size":{"unit":"rem","size":2,"sizes":[]},"classic_title_typography_font_weight":"400","__globals__":{"classic_excerpt_color":"globals\/colors?id=text","classic_meta_color":"globals\/colors?id=text"},"classic_thumbnail_size_size":"full","classic_item_ratio":{"unit":"px","size":0.5,"sizes":[]},"classic_title_typography_font_size_mobile":{"unit":"rem","size":2,"sizes":[]},"pagination_typography_typography":"custom","pagination_typography_font_family":"Work Sans","pagination_typography_font_size":{"unit":"rem","size":1,"sizes":[]},"pagination_typography_font_weight":"400","pagination_spacing":{"unit":"px","size":40,"sizes":[]},"pagination_spacing_top":{"unit":"px","size":40,"sizes":[]}},"elements":[],"isInner":false,"widgetType":"posts","elType":"widget"}],"isInner":false,"elType":"column"}],"isInner":false,"elType":"section"}],"settings":{"template":"elementor_header_footer"},"metadata":[]}